sharepoint_stuff.py
sharepoint_stuff-0.0.6.dist-info/LICENSE
sharepoint_stuff-0.0.6.dist-info/METADATA
sharepoint_stuff-0.0.6.dist-info/WHEEL
sharepoint_stuff-0.0.6.dist-info/top_level.txt
sharepoint_stuff-0.0.6.dist-info/RECORD
