Metadata-Version: 2.1
Name: sharepoint-stuff
Version: 0.0.6
Summary: Package that adds a range of functionality for working with sharepoint sites - under constant development
Home-page: https://github.com/george-oconnor/sharepoint-stuff
Author: george.oconnor (George O' Connor)
Author-email: <george@georgestools.com>
Keywords: python,sharepoint,upload,sharepoint site,download,office,office365,microsoft,microsoft365,azure,site
Classifier: Development Status :: 3 - Alpha
Classifier: Intended Audience :: Developers
Classifier: Programming Language :: Python :: 3
Classifier: Operating System :: OS Independent
Classifier: License :: OSI Approved :: MIT License
License-File: LICENSE
Requires-Dist: Office365-REST-Python-Client
Requires-Dist: office365
